README.md
setup.cfg
setup.py
tracemoepy/__init__.py
tracemoepy/async_trace.py
tracemoepy/tracemoe.py
tracemoepy.egg-info/PKG-INFO
tracemoepy.egg-info/SOURCES.txt
tracemoepy.egg-info/dependency_links.txt
tracemoepy.egg-info/requires.txt
tracemoepy.egg-info/top_level.txt
tracemoepy/errors/__init__.py
tracemoepy/helpers/__init__.py
tracemoepy/helpers/constants.py