Metadata-Version: 2.1
Name: tracemoepy
Version: 3.7
Summary: Trace.moe python wrapper
Home-page: https://github.com/DragSama/tracemoepy
License: UNKNOWN
Download-URL: https://github.com/DragSama/tracemoepy/releases
Platform: UNKNOWN
Classifier: Programming Language :: Python :: 3
Classifier: License :: OSI Approved :: GNU Lesser General Public License v3 (LGPLv3)
Classifier: Operating System :: OS Independent
Requires-Python: >=3.6
